sgid_client/IdTokenVerifier.py
sgid_client/SgidClient.py
sgid_client/__init__.py
sgid_client/decrypt_data.py
sgid_client/error.py
sgid_client/generators.py
sgid_client/util.py
sgid_client/validation.py
sgid_client-0.3.0.dist-info/LICENSE
sgid_client-0.3.0.dist-info/METADATA
sgid_client-0.3.0.dist-info/WHEEL
sgid_client-0.3.0.dist-info/RECORD
