Metadata-Version: 2.1
Name: sgid-client
Version: 0.3.0
Summary: The official Python SDK for sgID
Home-page: https://id.gov.sg
License: MIT
Author: Open Government Products
Requires-Python: >=3.11,<4.0
Classifier: License :: OSI Approved :: MIT License
Classifier: Programming Language :: Python :: 3
Classifier: Programming Language :: Python :: 3.11
Requires-Dist: jwcrypto (==1.4.2)
Requires-Dist: pycryptodome (==3.17)
Requires-Dist: requests (==2.31.0)
Project-URL: Documentation, https://docs.id.gov.sg
Project-URL: Repository, https://github.com/opengovsg/sgid-client-python
